gie/__init__.py
gie/agsi_mappings.py
gie/alsi_mappings.py
gie/exceptions.py
gie/gie.py
gie_py-0.4.6.dist-info/licenses/LICENSE.md
gie_py-0.4.6.dist-info/METADATA
gie_py-0.4.6.dist-info/WHEEL
gie_py-0.4.6.dist-info/top_level.txt
gie_py-0.4.6.dist-info/RECORD
