Metadata-Version: 2.4
Name: gie-py
Version: 0.4.6
Summary: A python API wrapper for alsi.gie.eu and agsi.gie.eu
Home-page: https://github.com/fboerman/gie-py
Author: Frank Boerman
Author-email: frank@fboerman.nl
License: MIT
Keywords: GIE data api energy gas
Classifier: Development Status :: 3 - Alpha
Classifier: Intended Audience :: Developers
Classifier: Topic :: Scientific/Engineering
Classifier: License :: OSI Approved :: MIT License
Classifier: Programming Language :: Python :: 3.8
Classifier: Programming Language :: Python :: 3.9
License-File: LICENSE.md
Requires-Dist: requests
Requires-Dist: pandas
Dynamic: author
Dynamic: author-email
Dynamic: classifier
Dynamic: description
Dynamic: description-content-type
Dynamic: home-page
Dynamic: keywords
Dynamic: license
Dynamic: license-file
Dynamic: requires-dist
Dynamic: summary
